[
  {
    "Type": "BodySetup",
    "Name": "BodySetup_0",
    "Outer": "SM_Damselfish",
    "Class": "UScriptClass'BodySetup'",
    "Properties": {
      "DefaultInstance": {
        "ObjectType": "ECC_WorldStatic",
        "CollisionProfileName": "BlockAll",
        "CollisionResponses": {
          "ResponseArray": [
            {
              "Channel": "PhysicalSurface",
              "Response": "ECR_Block"
            }
          ]
        }
      }
    },
    "BodySetupGuid": "EA7B7D604039E312F4F9EF9C55548E38",
    "CookedFormatData": {
      "PhysXPC": {
        "BulkDataFlags": "BULKDATA_SingleUse | BULKDATA_ForceInlinePayload",
        "ElementCount": 29365,
        "SizeOnDisk": 29365,
        "OffsetInFile": "0x1B0DC"
      }
    }
  },
  {
    "Type": "NavCollision",
    "Name": "NavCollision_0",
    "Outer": "SM_Damselfish",
    "Class": "UScriptClass'NavCollision'",
    "CookedFormatData": {
      "NavCollision_X": {
        "BulkDataFlags": "BULKDATA_SingleUse | BULKDATA_ForceInlinePayload",
        "ElementCount": 21,
        "SizeOnDisk": 21,
        "OffsetInFile": "0x223D9"
      }
    }
  },
  {
    "Type": "StaticMesh",
    "Name": "SM_Damselfish",
    "Class": "UScriptClass'StaticMesh'",
    "Properties": {
      "StaticMaterials": [
        {
          "MaterialInterface": {
            "ObjectName": "MaterialInstanceConstant'MI_Damselfish'",
            "ObjectPath": "ProjectCoral/Content/ProjectCoral/Characters/Common/Animations/Animal/Fish/Damselfish/MI_Damselfish.0"
          },
          "MaterialSlotName": "WorldGridMaterial",
          "ImportedMaterialSlotName": "WorldGridMaterial",
          "UVChannelData": {
            "bInitialized": true,
            "bOverrideDensities": false,
            "LocalUVDensities": 445.9793,
            "LocalUVDensities": 0.0,
            "LocalUVDensities": 0.0,
            "LocalUVDensities": 0.0
          }
        }
      ],
      "LightMapResolution": 64,
      "LightMapCoordinateIndex": 1,
      "ExtendedBounds": {
        "Origin": {
          "X": -0.63182545,
          "Y": -26.74456,
          "Z": -2.109476
        },
        "BoxExtent": {
          "X": 15.192981,
          "Y": 26.790268,
          "Z": 20.612381
        },
        "SphereRadius": 28.374641
      }
    },
    "BodySetup": {
      "ObjectName": "BodySetup'SM_Damselfish:BodySetup_0'",
      "ObjectPath": "ProjectCoral/Content/ProjectCoral/Characters/Common/Animations/Animal/Fish/Damselfish/SM_Damselfish.0"
    },
    "NavCollision": {
      "ObjectName": "NavCollision'SM_Damselfish:NavCollision_0'",
      "ObjectPath": "ProjectCoral/Content/ProjectCoral/Characters/Common/Animations/Animal/Fish/Damselfish/SM_Damselfish.1"
    },
    "LightingGuid": "5E6FE3E6-49B88D9E-0964018B-51C3C009",
    "RenderData": {
      "LODs": [
        {
          "Sections": [
            {
              "MaterialIndex": 0,
              "FirstIndex": 0,
              "NumTriangles": 1044,
              "MinVertexIndex": 0,
              "MaxVertexIndex": 677,
              "bEnableCollision": true,
              "bCastShadow": true,
              "bForceOpaque": false,
              "bVisibleInRayTracing": true
            }
          ],
          "MaxDeviation": 0.0,
          "PositionVertexBuffer": {
            "Stride": 12,
            "NumVertices": 678
          },
          "VertexBuffer": {
            "NumTexCoords": 2,
            "NumVertices": 678,
            "Strides": -1,
            "UseHighPrecisionTangentBasis": false,
            "UseFullPrecisionUVs": true
          },
          "ColorVertexBuffer": {
            "Stride": 0,
            "NumVertices": 0
          }
        }
      ],
      "Bounds": {
        "Origin": {
          "X": -0.63182545,
          "Y": -26.74456,
          "Z": -2.109476
        },
        "BoxExtent": {
          "X": 15.192981,
          "Y": 26.790268,
          "Z": 20.612381
        },
        "SphereRadius": 28.374641
      },
      "bLODsShareStaticLighting": true,
      "ScreenSize": [
        1.0,
        0.0,
        0.0,
        0.0,
        0.0,
        0.0,
        0.0,
        0.0
      ]
    }
  }
]