[
  {
    "Type": "DataTable",
    "Name": "DT_ShopMerfolkGeneralStore",
    "Class": "UScriptClass'DataTable'",
    "Properties": {
      "RowStruct": {
        "ObjectName": "ScriptStruct'C_ShopItemData'",
        "ObjectPath": "/Script/ProjectCoral"
      }
    },
    "Rows": {
      "top_lagoonTenunRegalia": {
        "allowedSeasons": [],
        "forbiddenSeasons": [],
        "allowedDays": [],
        "forbiddenDays": [],
        "availableSinceDate": false,
        "sinceDate": {
          "day": 1,
          "season": "EC_Season::None",
          "year": 1
        },
        "availableTillDate": false,
        "tillDate": {
          "day": 1,
          "season": "EC_Season::None",
          "year": 1
        },
        "availableDuringTime": false,
        "timeRange": {
          "fromTime": {
            "hours": 0,
            "minutes": 0
          },
          "toTime": {
            "hours": 0,
            "minutes": 0
          }
        },
        "allowedWeather": [],
        "forbiddenWeather": [],
        "enable": true,
        "townRank": 0,
        "item": {
          "data": {
            "DataTable": {
              "ObjectName": "DataTable'DT_InventoryItems'",
              "ObjectPath": "ProjectCoral/Content/ProjectCoral/Core/Data/DT_InventoryItems.0"
            },
            "RowName": "item_120410"
          },
          "itemID": "item_120410"
        },
        "useCustomName": false,
        "shopItemName": {
          "CultureInvariantString": null
        },
        "useCustomIcon": false,
        "customIcon": {
          "AssetPathName": "None",
          "SubPathString": ""
        },
        "useCustomCategory": false,
        "customCategory": {
          "CultureInvariantString": null
        },
        "useCustomDescription": false,
        "customDescription": {
          "CultureInvariantString": null
        },
        "useCategory": true,
        "category": "EC_ItemCategory::Clothes",
        "priority": 0,
        "priceOverride": 0,
        "tag": []
      },
      "top_imperialTenunRegalia": {
        "allowedSeasons": [],
        "forbiddenSeasons": [],
        "allowedDays": [],
        "forbiddenDays": [],
        "availableSinceDate": false,
        "sinceDate": {
          "day": 1,
          "season": "EC_Season::None",
          "year": 1
        },
        "availableTillDate": false,
        "tillDate": {
          "day": 1,
          "season": "EC_Season::None",
          "year": 1
        },
        "availableDuringTime": false,
        "timeRange": {
          "fromTime": {
            "hours": 0,
            "minutes": 0
          },
          "toTime": {
            "hours": 0,
            "minutes": 0
          }
        },
        "allowedWeather": [],
        "forbiddenWeather": [],
        "enable": true,
        "townRank": 0,
        "item": {
          "data": {
            "DataTable": {
              "ObjectName": "DataTable'DT_InventoryItems'",
              "ObjectPath": "ProjectCoral/Content/ProjectCoral/Core/Data/DT_InventoryItems.0"
            },
            "RowName": "item_120411"
          },
          "itemID": "item_120411"
        },
        "useCustomName": false,
        "shopItemName": {
          "CultureInvariantString": null
        },
        "useCustomIcon": false,
        "customIcon": {
          "AssetPathName": "None",
          "SubPathString": ""
        },
        "useCustomCategory": false,
        "customCategory": {
          "CultureInvariantString": null
        },
        "useCustomDescription": false,
        "customDescription": {
          "CultureInvariantString": null
        },
        "useCategory": true,
        "category": "EC_ItemCategory::Clothes",
        "priority": 0,
        "priceOverride": 0,
        "tag": []
      },
      "top_bronzeTenunRegalia": {
        "allowedSeasons": [],
        "forbiddenSeasons": [],
        "allowedDays": [],
        "forbiddenDays": [],
        "availableSinceDate": false,
        "sinceDate": {
          "day": 1,
          "season": "EC_Season::None",
          "year": 1
        },
        "availableTillDate": false,
        "tillDate": {
          "day": 1,
          "season": "EC_Season::None",
          "year": 1
        },
        "availableDuringTime": false,
        "timeRange": {
          "fromTime": {
            "hours": 0,
            "minutes": 0
          },
          "toTime": {
            "hours": 0,
            "minutes": 0
          }
        },
        "allowedWeather": [],
        "forbiddenWeather": [],
        "enable": true,
        "townRank": 0,
        "item": {
          "data": {
            "DataTable": {
              "ObjectName": "DataTable'DT_InventoryItems'",
              "ObjectPath": "ProjectCoral/Content/ProjectCoral/Core/Data/DT_InventoryItems.0"
            },
            "RowName": "item_120412"
          },
          "itemID": "item_120412"
        },
        "useCustomName": false,
        "shopItemName": {
          "CultureInvariantString": null
        },
        "useCustomIcon": false,
        "customIcon": {
          "AssetPathName": "None",
          "SubPathString": ""
        },
        "useCustomCategory": false,
        "customCategory": {
          "CultureInvariantString": null
        },
        "useCustomDescription": false,
        "customDescription": {
          "CultureInvariantString": null
        },
        "useCategory": true,
        "category": "EC_ItemCategory::Clothes",
        "priority": 0,
        "priceOverride": 0,
        "tag": []
      },
      "top_lagoonNaganianGarments": {
        "allowedSeasons": [],
        "forbiddenSeasons": [],
        "allowedDays": [],
        "forbiddenDays": [],
        "availableSinceDate": false,
        "sinceDate": {
          "day": 1,
          "season": "EC_Season::None",
          "year": 1
        },
        "availableTillDate": false,
        "tillDate": {
          "day": 1,
          "season": "EC_Season::None",
          "year": 1
        },
        "availableDuringTime": false,
        "timeRange": {
          "fromTime": {
            "hours": 0,
            "minutes": 0
          },
          "toTime": {
            "hours": 0,
            "minutes": 0
          }
        },
        "allowedWeather": [],
        "forbiddenWeather": [],
        "enable": true,
        "townRank": 0,
        "item": {
          "data": {
            "DataTable": {
              "ObjectName": "DataTable'DT_InventoryItems'",
              "ObjectPath": "ProjectCoral/Content/ProjectCoral/Core/Data/DT_InventoryItems.0"
            },
            "RowName": "item_120413"
          },
          "itemID": "item_120413"
        },
        "useCustomName": false,
        "shopItemName": {
          "CultureInvariantString": null
        },
        "useCustomIcon": false,
        "customIcon": {
          "AssetPathName": "None",
          "SubPathString": ""
        },
        "useCustomCategory": false,
        "customCategory": {
          "CultureInvariantString": null
        },
        "useCustomDescription": false,
        "customDescription": {
          "CultureInvariantString": null
        },
        "useCategory": true,
        "category": "EC_ItemCategory::Clothes",
        "priority": 0,
        "priceOverride": 0,
        "tag": []
      },
      "top_coastalNaganianGarments": {
        "allowedSeasons": [],
        "forbiddenSeasons": [],
        "allowedDays": [],
        "forbiddenDays": [],
        "availableSinceDate": false,
        "sinceDate": {
          "day": 1,
          "season": "EC_Season::None",
          "year": 1
        },
        "availableTillDate": false,
        "tillDate": {
          "day": 1,
          "season": "EC_Season::None",
          "year": 1
        },
        "availableDuringTime": false,
        "timeRange": {
          "fromTime": {
            "hours": 0,
            "minutes": 0
          },
          "toTime": {
            "hours": 0,
            "minutes": 0
          }
        },
        "allowedWeather": [],
        "forbiddenWeather": [],
        "enable": true,
        "townRank": 0,
        "item": {
          "data": {
            "DataTable": {
              "ObjectName": "DataTable'DT_InventoryItems'",
              "ObjectPath": "ProjectCoral/Content/ProjectCoral/Core/Data/DT_InventoryItems.0"
            },
            "RowName": "item_120414"
          },
          "itemID": "item_120414"
        },
        "useCustomName": false,
        "shopItemName": {
          "CultureInvariantString": null
        },
        "useCustomIcon": false,
        "customIcon": {
          "AssetPathName": "None",
          "SubPathString": ""
        },
        "useCustomCategory": false,
        "customCategory": {
          "CultureInvariantString": null
        },
        "useCustomDescription": false,
        "customDescription": {
          "CultureInvariantString": null
        },
        "useCategory": true,
        "category": "EC_ItemCategory::Clothes",
        "priority": 0,
        "priceOverride": 0,
        "tag": []
      },
      "top_tideNaganianGarments": {
        "allowedSeasons": [],
        "forbiddenSeasons": [],
        "allowedDays": [],
        "forbiddenDays": [],
        "availableSinceDate": false,
        "sinceDate": {
          "day": 1,
          "season": "EC_Season::None",
          "year": 1
        },
        "availableTillDate": false,
        "tillDate": {
          "day": 1,
          "season": "EC_Season::None",
          "year": 1
        },
        "availableDuringTime": false,
        "timeRange": {
          "fromTime": {
            "hours": 0,
            "minutes": 0
          },
          "toTime": {
            "hours": 0,
            "minutes": 0
          }
        },
        "allowedWeather": [],
        "forbiddenWeather": [],
        "enable": true,
        "townRank": 0,
        "item": {
          "data": {
            "DataTable": {
              "ObjectName": "DataTable'DT_InventoryItems'",
              "ObjectPath": "ProjectCoral/Content/ProjectCoral/Core/Data/DT_InventoryItems.0"
            },
            "RowName": "item_120415"
          },
          "itemID": "item_120415"
        },
        "useCustomName": false,
        "shopItemName": {
          "CultureInvariantString": null
        },
        "useCustomIcon": false,
        "customIcon": {
          "AssetPathName": "None",
          "SubPathString": ""
        },
        "useCustomCategory": false,
        "customCategory": {
          "CultureInvariantString": null
        },
        "useCustomDescription": false,
        "customDescription": {
          "CultureInvariantString": null
        },
        "useCategory": true,
        "category": "EC_ItemCategory::Clothes",
        "priority": 0,
        "priceOverride": 0,
        "tag": []
      },
      "top_stormClamcladGarments": {
        "allowedSeasons": [],
        "forbiddenSeasons": [],
        "allowedDays": [],
        "forbiddenDays": [],
        "availableSinceDate": false,
        "sinceDate": {
          "day": 1,
          "season": "EC_Season::None",
          "year": 1
        },
        "availableTillDate": false,
        "tillDate": {
          "day": 1,
          "season": "EC_Season::None",
          "year": 1
        },
        "availableDuringTime": false,
        "timeRange": {
          "fromTime": {
            "hours": 0,
            "minutes": 0
          },
          "toTime": {
            "hours": 0,
            "minutes": 0
          }
        },
        "allowedWeather": [],
        "forbiddenWeather": [],
        "enable": true,
        "townRank": 0,
        "item": {
          "data": {
            "DataTable": {
              "ObjectName": "DataTable'DT_InventoryItems'",
              "ObjectPath": "ProjectCoral/Content/ProjectCoral/Core/Data/DT_InventoryItems.0"
            },
            "RowName": "item_120416"
          },
          "itemID": "item_120416"
        },
        "useCustomName": false,
        "shopItemName": {
          "CultureInvariantString": null
        },
        "useCustomIcon": false,
        "customIcon": {
          "AssetPathName": "None",
          "SubPathString": ""
        },
        "useCustomCategory": false,
        "customCategory": {
          "CultureInvariantString": null
        },
        "useCustomDescription": false,
        "customDescription": {
          "CultureInvariantString": null
        },
        "useCategory": true,
        "category": "EC_ItemCategory::Clothes",
        "priority": 0,
        "priceOverride": 0,
        "tag": []
      },
      "top_moonlitClamcladGarments": {
        "allowedSeasons": [],
        "forbiddenSeasons": [],
        "allowedDays": [],
        "forbiddenDays": [],
        "availableSinceDate": false,
        "sinceDate": {
          "day": 1,
          "season": "EC_Season::None",
          "year": 1
        },
        "availableTillDate": false,
        "tillDate": {
          "day": 1,
          "season": "EC_Season::None",
          "year": 1
        },
        "availableDuringTime": false,
        "timeRange": {
          "fromTime": {
            "hours": 0,
            "minutes": 0
          },
          "toTime": {
            "hours": 0,
            "minutes": 0
          }
        },
        "allowedWeather": [],
        "forbiddenWeather": [],
        "enable": true,
        "townRank": 0,
        "item": {
          "data": {
            "DataTable": {
              "ObjectName": "DataTable'DT_InventoryItems'",
              "ObjectPath": "ProjectCoral/Content/ProjectCoral/Core/Data/DT_InventoryItems.0"
            },
            "RowName": "item_120417"
          },
          "itemID": "item_120417"
        },
        "useCustomName": false,
        "shopItemName": {
          "CultureInvariantString": null
        },
        "useCustomIcon": false,
        "customIcon": {
          "AssetPathName": "None",
          "SubPathString": ""
        },
        "useCustomCategory": false,
        "customCategory": {
          "CultureInvariantString": null
        },
        "useCustomDescription": false,
        "customDescription": {
          "CultureInvariantString": null
        },
        "useCategory": true,
        "category": "EC_ItemCategory::Clothes",
        "priority": 0,
        "priceOverride": 0,
        "tag": []
      },
      "top_scarletClamcladGarments": {
        "allowedSeasons": [],
        "forbiddenSeasons": [],
        "allowedDays": [],
        "forbiddenDays": [],
        "availableSinceDate": false,
        "sinceDate": {
          "day": 1,
          "season": "EC_Season::None",
          "year": 1
        },
        "availableTillDate": false,
        "tillDate": {
          "day": 1,
          "season": "EC_Season::None",
          "year": 1
        },
        "availableDuringTime": false,
        "timeRange": {
          "fromTime": {
            "hours": 0,
            "minutes": 0
          },
          "toTime": {
            "hours": 0,
            "minutes": 0
          }
        },
        "allowedWeather": [],
        "forbiddenWeather": [],
        "enable": true,
        "townRank": 0,
        "item": {
          "data": {
            "DataTable": {
              "ObjectName": "DataTable'DT_InventoryItems'",
              "ObjectPath": "ProjectCoral/Content/ProjectCoral/Core/Data/DT_InventoryItems.0"
            },
            "RowName": "item_120418"
          },
          "itemID": "item_120418"
        },
        "useCustomName": false,
        "shopItemName": {
          "CultureInvariantString": null
        },
        "useCustomIcon": false,
        "customIcon": {
          "AssetPathName": "None",
          "SubPathString": ""
        },
        "useCustomCategory": false,
        "customCategory": {
          "CultureInvariantString": null
        },
        "useCustomDescription": false,
        "customDescription": {
          "CultureInvariantString": null
        },
        "useCategory": true,
        "category": "EC_ItemCategory::Clothes",
        "priority": 0,
        "priceOverride": 0,
        "tag": []
      },
      "top_royalSilkGarments": {
        "allowedSeasons": [],
        "forbiddenSeasons": [],
        "allowedDays": [],
        "forbiddenDays": [],
        "availableSinceDate": false,
        "sinceDate": {
          "day": 1,
          "season": "EC_Season::None",
          "year": 1
        },
        "availableTillDate": false,
        "tillDate": {
          "day": 1,
          "season": "EC_Season::None",
          "year": 1
        },
        "availableDuringTime": false,
        "timeRange": {
          "fromTime": {
            "hours": 0,
            "minutes": 0
          },
          "toTime": {
            "hours": 0,
            "minutes": 0
          }
        },
        "allowedWeather": [],
        "forbiddenWeather": [],
        "enable": true,
        "townRank": 0,
        "item": {
          "data": {
            "DataTable": {
              "ObjectName": "DataTable'DT_InventoryItems'",
              "ObjectPath": "ProjectCoral/Content/ProjectCoral/Core/Data/DT_InventoryItems.0"
            },
            "RowName": "item_120418"
          },
          "itemID": "item_120418"
        },
        "useCustomName": false,
        "shopItemName": {
          "CultureInvariantString": null
        },
        "useCustomIcon": false,
        "customIcon": {
          "AssetPathName": "None",
          "SubPathString": ""
        },
        "useCustomCategory": false,
        "customCategory": {
          "CultureInvariantString": null
        },
        "useCustomDescription": false,
        "customDescription": {
          "CultureInvariantString": null
        },
        "useCategory": true,
        "category": "EC_ItemCategory::Clothes",
        "priority": 0,
        "priceOverride": 0,
        "tag": []
      },
      "top_kelpSilkGarments": {
        "allowedSeasons": [],
        "forbiddenSeasons": [],
        "allowedDays": [],
        "forbiddenDays": [],
        "availableSinceDate": false,
        "sinceDate": {
          "day": 1,
          "season": "EC_Season::None",
          "year": 1
        },
        "availableTillDate": false,
        "tillDate": {
          "day": 1,
          "season": "EC_Season::None",
          "year": 1
        },
        "availableDuringTime": false,
        "timeRange": {
          "fromTime": {
            "hours": 0,
            "minutes": 0
          },
          "toTime": {
            "hours": 0,
            "minutes": 0
          }
        },
        "allowedWeather": [],
        "forbiddenWeather": [],
        "enable": true,
        "townRank": 0,
        "item": {
          "data": {
            "DataTable": {
              "ObjectName": "DataTable'DT_InventoryItems'",
              "ObjectPath": "ProjectCoral/Content/ProjectCoral/Core/Data/DT_InventoryItems.0"
            },
            "RowName": "item_120420"
          },
          "itemID": "item_120420"
        },
        "useCustomName": false,
        "shopItemName": {
          "CultureInvariantString": null
        },
        "useCustomIcon": false,
        "customIcon": {
          "AssetPathName": "None",
          "SubPathString": ""
        },
        "useCustomCategory": false,
        "customCategory": {
          "CultureInvariantString": null
        },
        "useCustomDescription": false,
        "customDescription": {
          "CultureInvariantString": null
        },
        "useCategory": true,
        "category": "EC_ItemCategory::Clothes",
        "priority": 0,
        "priceOverride": 0,
        "tag": []
      },
      "top_bronzeSilkGarments": {
        "allowedSeasons": [],
        "forbiddenSeasons": [],
        "allowedDays": [],
        "forbiddenDays": [],
        "availableSinceDate": false,
        "sinceDate": {
          "day": 1,
          "season": "EC_Season::None",
          "year": 1
        },
        "availableTillDate": false,
        "tillDate": {
          "day": 1,
          "season": "EC_Season::None",
          "year": 1
        },
        "availableDuringTime": false,
        "timeRange": {
          "fromTime": {
            "hours": 0,
            "minutes": 0
          },
          "toTime": {
            "hours": 0,
            "minutes": 0
          }
        },
        "allowedWeather": [],
        "forbiddenWeather": [],
        "enable": true,
        "townRank": 0,
        "item": {
          "data": {
            "DataTable": {
              "ObjectName": "DataTable'DT_InventoryItems'",
              "ObjectPath": "ProjectCoral/Content/ProjectCoral/Core/Data/DT_InventoryItems.0"
            },
            "RowName": "item_120421"
          },
          "itemID": "item_120421"
        },
        "useCustomName": false,
        "shopItemName": {
          "CultureInvariantString": null
        },
        "useCustomIcon": false,
        "customIcon": {
          "AssetPathName": "None",
          "SubPathString": ""
        },
        "useCustomCategory": false,
        "customCategory": {
          "CultureInvariantString": null
        },
        "useCustomDescription": false,
        "customDescription": {
          "CultureInvariantString": null
        },
        "useCategory": true,
        "category": "EC_ItemCategory::Clothes",
        "priority": 0,
        "priceOverride": 0,
        "tag": []
      },
      "top_azurePlateArmor": {
        "allowedSeasons": [],
        "forbiddenSeasons": [],
        "allowedDays": [],
        "forbiddenDays": [],
        "availableSinceDate": false,
        "sinceDate": {
          "day": 1,
          "season": "EC_Season::None",
          "year": 1
        },
        "availableTillDate": false,
        "tillDate": {
          "day": 1,
          "season": "EC_Season::None",
          "year": 1
        },
        "availableDuringTime": false,
        "timeRange": {
          "fromTime": {
            "hours": 0,
            "minutes": 0
          },
          "toTime": {
            "hours": 0,
            "minutes": 0
          }
        },
        "allowedWeather": [],
        "forbiddenWeather": [],
        "enable": true,
        "townRank": 0,
        "item": {
          "data": {
            "DataTable": {
              "ObjectName": "DataTable'DT_InventoryItems'",
              "ObjectPath": "ProjectCoral/Content/ProjectCoral/Core/Data/DT_InventoryItems.0"
            },
            "RowName": "item_120422"
          },
          "itemID": "item_120422"
        },
        "useCustomName": false,
        "shopItemName": {
          "CultureInvariantString": null
        },
        "useCustomIcon": false,
        "customIcon": {
          "AssetPathName": "None",
          "SubPathString": ""
        },
        "useCustomCategory": false,
        "customCategory": {
          "CultureInvariantString": null
        },
        "useCustomDescription": false,
        "customDescription": {
          "CultureInvariantString": null
        },
        "useCategory": true,
        "category": "EC_ItemCategory::Clothes",
        "priority": 0,
        "priceOverride": 0,
        "tag": []
      },
      "top_ironcladPlateArmor": {
        "allowedSeasons": [],
        "forbiddenSeasons": [],
        "allowedDays": [],
        "forbiddenDays": [],
        "availableSinceDate": false,
        "sinceDate": {
          "day": 1,
          "season": "EC_Season::None",
          "year": 1
        },
        "availableTillDate": false,
        "tillDate": {
          "day": 1,
          "season": "EC_Season::None",
          "year": 1
        },
        "availableDuringTime": false,
        "timeRange": {
          "fromTime": {
            "hours": 0,
            "minutes": 0
          },
          "toTime": {
            "hours": 0,
            "minutes": 0
          }
        },
        "allowedWeather": [],
        "forbiddenWeather": [],
        "enable": true,
        "townRank": 0,
        "item": {
          "data": {
            "DataTable": {
              "ObjectName": "DataTable'DT_InventoryItems'",
              "ObjectPath": "ProjectCoral/Content/ProjectCoral/Core/Data/DT_InventoryItems.0"
            },
            "RowName": "item_120423"
          },
          "itemID": "item_120423"
        },
        "useCustomName": false,
        "shopItemName": {
          "CultureInvariantString": null
        },
        "useCustomIcon": false,
        "customIcon": {
          "AssetPathName": "None",
          "SubPathString": ""
        },
        "useCustomCategory": false,
        "customCategory": {
          "CultureInvariantString": null
        },
        "useCustomDescription": false,
        "customDescription": {
          "CultureInvariantString": null
        },
        "useCategory": true,
        "category": "EC_ItemCategory::Clothes",
        "priority": 0,
        "priceOverride": 0,
        "tag": []
      },
      "top_bronzePlateArmor": {
        "allowedSeasons": [],
        "forbiddenSeasons": [],
        "allowedDays": [],
        "forbiddenDays": [],
        "availableSinceDate": false,
        "sinceDate": {
          "day": 1,
          "season": "EC_Season::None",
          "year": 1
        },
        "availableTillDate": false,
        "tillDate": {
          "day": 1,
          "season": "EC_Season::None",
          "year": 1
        },
        "availableDuringTime": false,
        "timeRange": {
          "fromTime": {
            "hours": 0,
            "minutes": 0
          },
          "toTime": {
            "hours": 0,
            "minutes": 0
          }
        },
        "allowedWeather": [],
        "forbiddenWeather": [],
        "enable": true,
        "townRank": 0,
        "item": {
          "data": {
            "DataTable": {
              "ObjectName": "DataTable'DT_InventoryItems'",
              "ObjectPath": "ProjectCoral/Content/ProjectCoral/Core/Data/DT_InventoryItems.0"
            },
            "RowName": "item_120424"
          },
          "itemID": "item_120424"
        },
        "useCustomName": false,
        "shopItemName": {
          "CultureInvariantString": null
        },
        "useCustomIcon": false,
        "customIcon": {
          "AssetPathName": "None",
          "SubPathString": ""
        },
        "useCustomCategory": false,
        "customCategory": {
          "CultureInvariantString": null
        },
        "useCustomDescription": false,
        "customDescription": {
          "CultureInvariantString": null
        },
        "useCategory": true,
        "category": "EC_ItemCategory::Clothes",
        "priority": 0,
        "priceOverride": 0,
        "tag": []
      }
    }
  }
]