[
  {
    "Type": "BodySetup",
    "Name": "BodySetup_0",
    "Outer": "SM_CannonballJellyfish",
    "Class": "UScriptClass'BodySetup'",
    "Properties": {
      "AggGeom": {
        "ConvexElems": [
          {
            "VertexData": [
              {
                "X": 28.624077,
                "Y": 11.7509165,
                "Z": 19.999077
              },
              {
                "X": 28.624077,
                "Y": -11.75092,
                "Z": 19.999077
              },
              {
                "X": 28.624077,
                "Y": -11.750923,
                "Z": 48.125916
              },
              {
                "X": 28.624077,
                "Y": 11.750919,
                "Z": 48.125916
              },
              {
                "X": -28.624077,
                "Y": -11.750923,
                "Z": 19.999079
              },
              {
                "X": -28.624077,
                "Y": 11.750931,
                "Z": 19.99908
              },
              {
                "X": -28.624077,
                "Y": 11.750925,
                "Z": 48.12592
              },
              {
                "X": -28.624077,
                "Y": -11.750921,
                "Z": 48.125923
              },
              {
                "X": -11.866331,
                "Y": 28.508677,
                "Z": 21.508675
              },
              {
                "X": 11.866318,
                "Y": 28.508677,
                "Z": 21.508677
              },
              {
                "X": 11.86632,
                "Y": 28.508677,
                "Z": 47.741314
              },
              {
                "X": -11.866333,
                "Y": 28.508677,
                "Z": 47.741318
              },
              {
                "X": 11.866301,
                "Y": -28.508696,
                "Z": 22.133698
              },
              {
                "X": -11.8663025,
                "Y": -28.508696,
                "Z": 22.133698
              },
              {
                "X": -11.8663025,
                "Y": -28.508696,
                "Z": 47.74131
              },
              {
                "X": 11.8663025,
                "Y": -28.508696,
                "Z": 47.74131
              },
              {
                "X": -12.79058,
                "Y": 12.290566,
                "Z": 63.959427
              },
              {
                "X": 12.7905655,
                "Y": 12.290568,
                "Z": 63.959427
              },
              {
                "X": 12.790571,
                "Y": -12.290583,
                "Z": 63.959427
              },
              {
                "X": -12.790575,
                "Y": -12.290579,
                "Z": 63.959427
              },
              {
                "X": -13.099013,
                "Y": -10.8490095,
                "Z": 4.4740133
              },
              {
                "X": 13.099015,
                "Y": -10.849008,
                "Z": 4.4740133
              },
              {
                "X": 13.099013,
                "Y": 11.474016,
                "Z": 4.4740133
              },
              {
                "X": -13.09901,
                "Y": 11.474015,
                "Z": 4.4740133
              },
              {
                "X": 20.4375,
                "Y": 19.937504,
                "Z": 56.312496
              },
              {
                "X": -20.437508,
                "Y": 19.937504,
                "Z": 56.312496
              },
              {
                "X": 21.312496,
                "Y": -19.062496,
                "Z": 12.687498
              },
              {
                "X": -21.3125,
                "Y": -19.062498,
                "Z": 12.687503
              },
              {
                "X": -21.000004,
                "Y": 19.375004,
                "Z": 12.375005
              },
              {
                "X": 20.999998,
                "Y": 19.374996,
                "Z": 12.374996
              },
              {
                "X": -20.437504,
                "Y": -19.9375,
                "Z": 56.3125
              },
              {
                "X": 20.437496,
                "Y": -19.937504,
                "Z": 56.312496
              }
            ],
            "IndexData": [
              0,
              1,
              2,
              0,
              2,
              3,
              4,
              5,
              6,
              4,
              6,
              7,
              8,
              9,
              10,
              8,
              10,
              11,
              12,
              13,
              14,
              12,
              14,
              15,
              16,
              17,
              18,
              16,
              18,
              19,
              20,
              21,
              22,
              20,
              22,
              23,
              11,
              10,
              24,
              11,
              24,
              17,
              11,
              17,
              16,
              11,
              16,
              25,
              26,
              21,
              20,
              26,
              20,
              27,
              26,
              27,
              13,
              26,
              13,
              12,
              28,
              23,
              22,
              28,
              22,
              29,
              28,
              29,
              9,
              28,
              9,
              8,
              15,
              14,
              30,
              15,
              30,
              19,
              15,
              19,
              18,
              15,
              18,
              31,
              31,
              18,
              17,
              31,
              17,
              24,
              31,
              24,
              3,
              31,
              3,
              2,
              27,
              20,
              23,
              27,
              23,
              28,
              27,
              28,
              5,
              27,
              5,
              4,
              29,
              22,
              21,
              29,
              21,
              26,
              29,
              26,
              1,
              29,
              1,
              0,
              25,
              16,
              19,
              25,
              19,
              30,
              25,
              30,
              7,
              25,
              7,
              6,
              29,
              0,
              3,
              29,
              3,
              24,
              29,
              24,
              10,
              29,
              10,
              9,
              27,
              4,
              7,
              27,
              7,
              30,
              27,
              30,
              14,
              27,
              14,
              13,
              26,
              12,
              15,
              26,
              15,
              31,
              26,
              31,
              2,
              26,
              2,
              1,
              28,
              8,
              11,
              28,
              11,
              25,
              28,
              25,
              6,
              28,
              6,
              5
            ],
            "ElemBox": {
              "Min": {
                "X": -28.624077,
                "Y": -28.508696,
                "Z": 4.4740133
              },
              "Max": {
                "X": 28.624077,
                "Y": 28.508677,
                "Z": 63.959427
              },
              "IsValid": 1
            },
            "Transform": {
              "Rotation": {
                "X": 0.0,
                "Y": 0.0,
                "Z": 0.0,
                "W": 1.0,
                "IsNormalized": true,
                "Size": 1.0,
                "SizeSquared": 1.0
              },
              "Translation": {
                "X": 0.0,
                "Y": 0.0,
                "Z": 0.0
              },
              "Scale3D": {
                "X": 1.0,
                "Y": 1.0,
                "Z": 1.0
              }
            },
            "RestOffset": 0.0,
            "Name": "None",
            "bContributeToMass": true,
            "CollisionEnabled": "ECollisionEnabled::QueryAndPhysics"
          }
        ]
      },
      "DefaultInstance": {
        "ObjectType": "ECC_WorldStatic",
        "CollisionProfileName": "BlockAll",
        "CollisionResponses": {
          "ResponseArray": [
            {
              "Channel": "PhysicalSurface",
              "Response": "ECR_Block"
            }
          ]
        }
      }
    },
    "BodySetupGuid": "87C1BCCC4765A16CAF05A49F9944FC8D",
    "CookedFormatData": {
      "PhysXPC": {
        "BulkDataFlags": "BULKDATA_SingleUse | BULKDATA_ForceInlinePayload",
        "ElementCount": 65631,
        "SizeOnDisk": 65631,
        "OffsetInFile": "0x37671"
      }
    }
  },
  {
    "Type": "NavCollision",
    "Name": "NavCollision_0",
    "Outer": "SM_CannonballJellyfish",
    "Class": "UScriptClass'NavCollision'",
    "CookedFormatData": {
      "NavCollision_X": {
        "BulkDataFlags": "BULKDATA_SingleUse | BULKDATA_ForceInlinePayload",
        "ElementCount": 1897,
        "SizeOnDisk": 1897,
        "OffsetInFile": "0x47718"
      }
    }
  },
  {
    "Type": "StaticMesh",
    "Name": "SM_CannonballJellyfish",
    "Class": "UScriptClass'StaticMesh'",
    "Properties": {
      "StaticMaterials": [
        {
          "MaterialInterface": {
            "ObjectName": "MaterialInstanceConstant'MI_OceanCritter_10m_2'",
            "ObjectPath": "ProjectCoral/Content/ProjectCoral/Characters/Animals/OceanCritter_10m/MI_OceanCritter_10m_2.0"
          },
          "MaterialSlotName": "MI_CannonballJellyfish_00",
          "ImportedMaterialSlotName": "MI_CannonballJellyfish_00",
          "UVChannelData": {
            "bInitialized": true,
            "bOverrideDensities": false,
            "LocalUVDensities": 194.30989,
            "LocalUVDensities": 134.79236,
            "LocalUVDensities": 0.0,
            "LocalUVDensities": 0.0
          }
        }
      ],
      "LightmapUVDensity": 134.79236,
      "LightMapResolution": 64,
      "LightMapCoordinateIndex": 1,
      "ExtendedBounds": {
        "Origin": {
          "X": 0.0,
          "Y": -1.1444092E-05,
          "Z": 34.21672
        },
        "BoxExtent": {
          "X": 28.524076,
          "Y": 28.408688,
          "Z": 29.642708
        },
        "SphereRadius": 32.01807
      }
    },
    "BodySetup": {
      "ObjectName": "BodySetup'SM_CannonballJellyfish:BodySetup_0'",
      "ObjectPath": "ProjectCoral/Content/ProjectCoral/Characters/Animals/OceanCritter_10m/SM_CannonballJellyfish.0"
    },
    "NavCollision": {
      "ObjectName": "NavCollision'SM_CannonballJellyfish:NavCollision_0'",
      "ObjectPath": "ProjectCoral/Content/ProjectCoral/Characters/Animals/OceanCritter_10m/SM_CannonballJellyfish.1"
    },
    "LightingGuid": "FA29E900-4E1317A9-7F3AFB84-B5A1DF9F",
    "RenderData": {
      "LODs": [
        {
          "Sections": [
            {
              "MaterialIndex": 0,
              "FirstIndex": 0,
              "NumTriangles": 2328,
              "MinVertexIndex": 0,
              "MaxVertexIndex": 1257,
              "bEnableCollision": true,
              "bCastShadow": true,
              "bForceOpaque": false,
              "bVisibleInRayTracing": true
            }
          ],
          "MaxDeviation": 0.0,
          "PositionVertexBuffer": {
            "Stride": 12,
            "NumVertices": 1258
          },
          "VertexBuffer": {
            "NumTexCoords": 2,
            "NumVertices": 1258,
            "Strides": -1,
            "UseHighPrecisionTangentBasis": false,
            "UseFullPrecisionUVs": false
          },
          "ColorVertexBuffer": {
            "Stride": 0,
            "NumVertices": 0
          }
        }
      ],
      "Bounds": {
        "Origin": {
          "X": 0.0,
          "Y": -1.1444092E-05,
          "Z": 34.21672
        },
        "BoxExtent": {
          "X": 28.524076,
          "Y": 28.408688,
          "Z": 29.642708
        },
        "SphereRadius": 32.01807
      },
      "bLODsShareStaticLighting": true,
      "ScreenSize": [
        1.0,
        0.0,
        0.0,
        0.0,
        0.0,
        0.0,
        0.0,
        0.0
      ]
    }
  }
]