{
  "id": "item_23047",
  "displayName": "Graines de pastèque",
  "price": 50,
  "sellPrice": 30,
  "sellAt": [
    "Sam"
  ],
  "stackable": true,
  "inventoryCategory": "Seeds",
  "displayKey": "Seeds",
  "description": "Planter en automne. Pousse en 11 jours. Peut donner une qualité régulière. ",
  "qualities": {},
  "iconName": "Watermelon_seeds_Sprite",
  "tags": [
    "income.farming"
  ],
  "artisanResult": [
    {
      "useCategory": false,
      "day": 0,
      "time": {
        "hours": 0,
        "minutes": 0
      },
      "additionalInput": [],
      "input": {
        "amount": 1,
        "item": {
          "id": "item_23046",
          "displayName": "Pastèque",
          "iconName": "Watermelon_Sprite"
        }
      },
      "output": {
        "amount": 1,
        "item": {
          "id": "item_23047",
          "displayName": "Graines de pastèque",
          "iconName": "Watermelon_seeds_Sprite"
        }
      },
      "genericInput": null
    }
  ]
}